PySimpleGUI4.py
pysimplegui4-4.80.7.dist-info/METADATA
pysimplegui4-4.80.7.dist-info/WHEEL
pysimplegui4-4.80.7.dist-info/licenses/LICENSE
pysimplegui4-4.80.7.dist-info/RECORD
