Metadata-Version: 2.4
Name: PySimpleGUI4
Version: 4.80.7
Summary: The free-forever and simple Python GUI framework
Project-URL: Source, https://github.com/yunluo/PySimpleGUI4
Author-email: yunluo <sp91@qq.com>
License-Expression: GPL-3.0-or-later
License-File: LICENSE
Keywords: GUI,PySimpleGui,UI,tkinter
Classifier: Development Status :: 5 - Production/Stable
Classifier: Intended Audience :: Developers
Classifier: License :: OSI Approved :: GNU General Public License v3 or later (GPLv3+)
Classifier: Operating System :: OS Independent
Classifier: Programming Language :: Python :: 3
Classifier: Programming Language :: Python :: 3.7
Classifier: Programming Language :: Python :: 3.8
Classifier: Programming Language :: Python :: 3.9
Classifier: Programming Language :: Python :: 3.10
Classifier: Programming Language :: Python :: 3.11
Classifier: Programming Language :: Python :: 3.12
Classifier: Programming Language :: Python :: 3.13
Requires-Python: >=3
